{
  "Seed": 1810315861,
  "Model": "sd_xl_base_1.0.safetensors",
  "Lora": null,
  "Steps": 28,
  "CfgMilli": 6500,
  "SamplerResolved": "dpmpp_2m",
  "SchedulerResolved": "karras",
  "PaletteSha256": null,
  "DiffuseSha256": "4e484df54e357bac2194297be5c2a891f3eeb19bf0ad6b8cff9aaad9341128b3",
  "NormalSha256": null,
  "Uid": "uid://bq37setmtwwpp",
  "HandFinished": false,
  "Status": "locked",
  "Provenance": {
    "drafts": "8-20 candidates generated locally via ComfyUI MCP; curated hard per art/pipeline/README.md",
    "paintoverNote": "round3 (anti-character/knight negatives) c0, clean single axe",
    "aiDisclosure": "AI-generated (SDXL base 1.0) diffuse, background-removed via BiRefNet (cutout.py); no normal map (flat menu icon per AssetSpec.NormalMap=false)"
  }
}
